s_opt . JUMP_ABSOLUTE JUMP_FORWARD \e__come_froms
_ifstmts_jump ::= \e_c_stmts_opt . JUMP_ABSOLUTE JUMP_FORWARD _come_froms
_ifstmts_jump ::= \e_c_stmts_opt . come_froms
_ifstmts_jump ::= c_stmts_opt . COME_FROM
_ifstmts_jump ::= c_stmts_opt . ELSE
_ifstmts_jump ::= c_stmts_opt . JUMP_ABSOLUTE JUMP_FORWARD \e__come_froms
_ifstmts_jump ::= c_stmts_opt . JUMP_ABSOLUTE JUMP_FORWARD _come_froms
_ifstmts_jump ::= c_stmts_opt . come_froms
_ifstmts_jumpl ::= c_stmts . JUMP_BACK
_stmts ::= _stmts . stmt
_stmts ::= _stmts stmt . 
_stmts ::= stmt . 
and ::= expr . JUMP_IF_FALSE_OR_POP expr \e_come_from_opt
and ::= expr . JUMP_IF_FALSE_OR_POP expr come_from_opt
and ::= expr . jifop_come_from expr
and ::= expr . jmp_false expr
and ::= expr . jmp_false expr COME_FROM
and ::= expr . jmp_false expr jmp_false
and ::= expr jmp_false . expr
and ::= expr jmp_false . expr COME_FROM
and ::= expr jmp_false . expr jmp_false
and ::= expr jmp_false expr . 
and ::= expr jmp_false expr . COME_FROM
and ::= expr jmp_false expr . jmp_false
and_not ::= expr . jmp_false expr POP_JUMP_IF_TRUE
and_not ::= expr jmp_false . expr POP_JUMP_IF_TRUE
and_not ::= expr jmp_false expr . POP_JUMP_IF_TRUE
assert2 ::= expr . jmp_true LOAD_GLOBAL expr CALL_FUNCTION_1 RAISE_VARARGS_1
assign ::= expr . DUP_TOP designList
assign ::= expr . store
assign ::= expr store . 
assign2 ::= expr . expr ROT_TWO store store
assign2 ::= expr expr . ROT_TWO store store
assign3 ::= expr . expr expr ROT_THREE ROT_TWO store store store
assign3 ::= expr expr . expr ROT_THREE ROT_TWO store store store
assign3 ::= expr expr expr . ROT_THREE ROT_TWO store store store
async_for_stmt38 ::= expr . async_for store for_block COME_FROM_FINALLY END_ASYNC_FOR
async_forelse_stmt38 ::= expr . GET_AITER SETUP_FINALLY GET_ANEXT LOAD_CONST YIELD_FROM POP_BLOCK store for_block COME_FROM_FINALLY END_ASYNC_FOR else_suite
attribute ::= expr . LOAD_ATTR
attribute37 ::= expr . LOAD_METHOD
attribute37 ::= expr LOAD_METHOD . 
aug_assign1 ::= expr . expr inplace_op ROT_THREE STORE_SUBSCR
aug_assign1 ::= expr . expr inplace_op store
aug_assign1 ::= expr expr . inplace_op ROT_THREE STORE_SUBSCR
aug_assign1 ::= expr expr . inplace_op store
aug_assign2 ::= expr . DUP_TOP LOAD_ATTR expr inplace_op ROT_TWO STORE_ATTR
await_expr ::= expr . GET_AWAITABLE LOAD_CONST YIELD_FROM
bin_op ::= expr . expr binary_operator
bin_op ::= expr expr . binary_operator
bin_op ::= expr expr binary_operator . 
binary_operator ::= BINARY_ADD . 
binary_operator ::= BINARY_SUBTRACT . 
break ::= POP_TOP . BREAK_LOOP
c_stmts ::= _stmts . 
c_stmts ::= _stmts . lastc_stmt
c_stmts_opt ::= c_stmts . 
call ::= expr . CALL_FUNCTION_0
call ::= expr . CALL_METHOD_0
call ::= expr . expr CALL_METHOD_1
call ::= expr . expr expr CALL_METHOD_2
call ::= expr . expr expr expr CALL_METHOD_3
call ::= expr . pos_arg CALL_FUNCTION_1
call ::= expr CALL_METHOD_0 . 
call ::= expr expr . CALL_METHOD_1
call ::= expr expr . expr CALL_METHOD_2
call ::= expr expr . expr expr CALL_METHOD_3
call ::= expr expr CALL_METHOD_1 . 
call ::= expr expr expr . CALL_METHOD_2
call ::= expr expr expr . expr CALL_METHOD_3
call ::= expr expr expr expr . CALL_METHOD_3
call ::= expr pos_arg . CALL_FUNCTION_1
call ::= expr pos_arg CALL_FUNCTION_1 . 
call_ex_kw4 ::= expr . expr expr CALL_FUNCTION_EX_KW
call_ex_kw4 ::= expr expr . expr CALL_FUNCTION_EX_KW
call_ex_kw4 ::= expr expr expr . CALL_FUNCTION_EX_KW
call_kw36 ::= expr . expr expr LOAD_CONST CALL_FUNCTION_KW_2
call_kw36 ::= expr expr . expr LOAD_CONST CALL_FUNCTION_KW_2
call_kw36 ::= expr expr expr . LOAD_CONST CALL_FUNCTION_KW_2
call_stmt ::= call . 
call_stmt ::= expr . POP_TOP
call_stmt ::= expr POP_TOP . 
classdefdeco1 ::= expr . classdefdeco1 CALL_FUNCTION_1
classdefdeco1 ::= expr . classdefdeco2 CALL_FUNCTION_1
come_from_loops ::= \e_come_from_loops . COME_FROM_LOOP
compare ::= compare_single . 
compare_chained ::= expr . compare_chained1 ROT_TWO POP_TOP \e__come_froms
compare_chained ::= expr . compare_chained1 ROT_TWO POP_TOP _come_froms
compare_chained1 ::= expr . DUP_TOP ROT_THREE COMPARE_OP JUMP_IF_FALSE_OR_POP compare_chained1 COME_FROM
compare_chained1 ::= expr . DUP_TOP ROT_THREE COMPARE_OP JUMP_IF_FALSE_OR_POP compare_chained2 COME_FROM
compare_chained1_false_37 ::= expr . DUP_TOP ROT_THREE COMPARE_OP POP_JUMP_IF_FALSE compare_chained2b_false_37 POP_TOP _jump COME_FROM
compare_chained1_false_37 ::= expr . DUP_TOP ROT_THREE COMPARE_OP POP_JUMP_IF_FALSE compare_chained2c_37 POP_TOP JUMP_FORWARD COME_FROM
compare_chained1a_37 ::= expr . DUP_TOP ROT_THREE COMPARE_OP POP_JUMP_IF_FALSE
compare_chained1a_37 ::= expr . DUP_TOP ROT_THREE COMPARE_OP POP_JUMP_IF_FALSE compare_chained2a_37 COME_FROM POP_TOP COME_FROM
compare_chained1b_false_37 ::= expr . DUP_TOP ROT_THREE COMPARE_OP POP_JUMP_IF_FALSE compare_chained2b_false_37 POP_TOP _jump COME_FROM
compare_chained1c_37 ::= expr . DUP_TOP ROT_THREE COMPARE_OP POP_JUMP_IF_FALSE compare_chained2a_37 POP_TOP
compare_chained2_false_37 ::= expr . DUP_TOP ROT_THREE COMPARE_OP POP_JUMP_IF_FALSE compare_chained2a_false_37 POP_TOP JUMP_BACK COME_FROM
compare_chained37 ::= expr . compare_chained1a_37
compare_chained37 ::= expr . compare_chained1c_37
compare_chained37_false ::= expr . compare_chained1_false_37
compare_chained37_false ::= expr . compare_chained1b_false_37
compare_chained37_false ::= expr . compare_chained2_false_37
compare_single ::= expr . expr COMPARE_OP
compare_single ::= expr expr . COMPARE_OP
compare_single ::= expr expr COMPARE_OP . 
continues ::= _stmts . lastl_stmt continue
expr ::= LOAD_CONST . 
expr ::= LOAD_DEREF . 
expr ::= LOAD_FAST . 
expr ::= LOAD_GLOBAL . 
expr ::= LOAD_STR . 
expr ::= attribute37 . 
expr ::= bin_op . 
expr ::= call . 
expr ::= compare . 
expr ::= formatted_value1 . 
expr ::= get_iter . 
expr ::= joined_str . 
expr_jit ::= expr . JUMP_IF_TRUE
expr_jitop ::= expr . JUMP_IF_TRUE_OR_POP
expr_jt ::= expr . jmp_true
expr_pjit ::= expr . POP_JUMP_IF_TRUE
expr_pjit_come_from ::= expr . POP_JUMP_IF_TRUE COME_FROM
expr_stmt ::= expr . POP_TOP
expr_stmt ::= expr POP_TOP . 
for38 ::= expr . get_for_iter store for_block
for38 ::= expr . get_for_iter store for_block JUMP_BACK
for38 ::= expr . get_for_iter store for_block JUMP_BACK POP_BLOCK
for38 ::= expr . get_iter store for_block JUMP_BACK
for38 ::= expr get_for_iter . store for_block
for38 ::= expr get_for_iter . store for_block JUMP_BACK
for38 ::= expr get_for_iter . store for_block JUMP_BACK POP_BLOCK
for38 ::= expr get_for_iter store . for_block
for38 ::= expr get_for_iter store . for_block JUMP_BACK
for38 ::= expr get_for_iter store . for_block JUMP_BACK POP_BLOCK
for38 ::= expr get_for_iter store for_block . 
for38 ::= expr get_for_iter store for_block . JUMP_BACK
for38 ::= expr get_for_iter store for_block . JUMP_BACK POP_BLOCK
for_block ::= \e__come_froms . l_stmts_opt _come_from_loops JUMP_BACK
for_block ::= \e__come_froms \e_l_stmts_opt . _come_from_loops JUMP_BACK
for_block ::= \e__come_froms l_stmts_opt . _come_from_loops JUMP_BACK
for_block ::= \e_l_stmts_opt . _come_froms JUMP_BACK
for_block ::= \e_l_stmts_opt . come_from_loops JUMP_BACK
for_block ::= \e_l_stmts_opt \e__come_froms . JUMP_BACK
for_block ::= \e_l_stmts_opt \e_come_from_loops . JUMP_BACK
for_block ::= l_stmts . 
for_block ::= l_stmts . JUMP_BACK
for_block ::= l_stmts_opt . _come_froms JUMP_BACK
for_block ::= l_stmts_opt . come_from_loops JUMP_BACK
for_block ::= l_stmts_opt \e__come_froms . JUMP_BACK
for_block ::= l_stmts_opt \e_come_from_loops . JUMP_BACK
forelselaststmt38 ::= expr . get_for_iter store for_block POP_BLOCK else_suitec
forelselaststmt38 ::= expr get_for_iter . store for_block POP_BLOCK else_suitec
forelselaststmt38 ::= expr get_for_iter store . for_block POP_BLOCK else_suitec
forelselaststmt38 ::= expr get_for_iter store for_block . POP_BLOCK else_suitec
forelselaststmtl38 ::= expr . get_for_iter store for_block POP_BLOCK else_suitel
forelselaststmtl38 ::= expr get_for_iter . store for_block POP_BLOCK else_suitel
forelselaststmtl38 ::= expr get_for_iter store . for_block POP_BLOCK else_suitel
forelselaststmtl38 ::= expr get_for_iter store for_block . POP_BLOCK else_suitel
forelsestmt38 ::= expr . get_for_iter store for_block JUMP_BACK \e__come_froms else_suite
forelsestmt38 ::= expr . get_for_iter store for_block JUMP_BACK _come_froms else_suite
forelsestmt38 ::= expr . get_for_iter store for_block POP_BLOCK else_suite
forelsestmt38 ::= expr get_for_iter . store for_block JUMP_BACK \e__come_froms else_suite
forelsestmt38 ::= expr get_for_iter . store for_block JUMP_BACK _come_froms else_suite
forelsestmt38 ::= expr get_for_iter . store for_block POP_BLOCK else_suite
forelsestmt38 ::= expr get_for_iter store . for_block JUMP_BACK \e__come_froms else_suite
forelsestmt38 ::= expr get_for_iter store . for_block JUMP_BACK _come_froms else_suite
forelsestmt38 ::= expr get_for_iter store . for_block POP_BLOCK else_suite
forelsestmt38 ::= expr get_for_iter store for_block . JUMP_BACK \e__come_froms else_suite
forelsestmt38 ::= expr get_for_iter store for_block . JUMP_BACK _come_froms else_suite
forelsestmt38 ::= expr get_for_iter store for_block . POP_BLOCK else_suite
formatted_value1 ::= expr . FORMAT_VALUE
formatted_value1 ::= expr FORMAT_VALUE . 
formatted_value_debug ::= LOAD_STR . formatted_value1 LOAD_STR BUILD_STRING_3
formatted_value_debug ::= LOAD_STR . formatted_value2 LOAD_STR BUILD_STRING_3
formatted_value_debug ::= LOAD_STR formatted_value1 . LOAD_STR BUILD_STRING_3
get_for_iter ::= GET_ITER . _come_froms FOR_ITER
get_for_iter ::= GET_ITER \e__come_froms . FOR_ITER
get_for_iter ::= GET_ITER \e__come_froms FOR_ITER . 
get_iter ::= expr . GET_ITER
get_iter ::= expr GET_ITER . 
if_exp ::= expr . jmp_false expr jf_cf expr COME_FROM
if_exp ::= expr . jmp_false expr jump_absolute_else expr
if_exp ::= expr jmp_false . expr jf_cf expr COME_FROM
if_exp ::= expr jmp_false . expr jump_absolute_else expr
if_exp ::= expr jmp_false expr . jf_cf expr COME_FROM
if_exp ::= expr jmp_false expr . jump_absolute_else expr
if_exp37 ::= expr . expr jf_cfs expr COME_FROM
if_exp37 ::= expr expr . jf_cfs expr COME_FROM
if_exp_37b ::= expr . jmp_false expr POP_JUMP_IF_FALSE jump_forward_else expr
if_exp_37b ::= expr jmp_false . expr POP_JUMP_IF_FALSE jump_forward_else expr
if_exp_37b ::= expr jmp_false expr . POP_JUMP_IF_FALSE jump_forward_else expr
if_exp_lambda ::= expr . jmp_false expr return_if_lambda return_stmt_lambda LAMBDA_MARKER
if_exp_lambda ::= expr jmp_false . expr return_if_lambda return_stmt_lambda LAMBDA_MARKER
if_exp_lambda ::= expr jmp_false expr . return_if_lambda return_stmt_lambda LAMBDA_MARKER
if_exp_not ::= expr . jmp_true expr jump_forward_else expr COME_FROM
if_exp_not_lambda ::= expr . jmp_true expr return_if_lambda return_stmt_lambda LAMBDA_MARKER
if_exp_true ::= expr . JUMP_FORWARD expr COME_FROM
ifelsestmt ::= testexpr . c_stmts come_froms else_suite come_froms
ifelsestmt ::= testexpr . c_stmts_opt JUMP_FORWARD else_suite \e__come_froms
ifelsestmt ::= testexpr . c_stmts_opt JUMP_FORWARD else_suite \e_opt_come_from_except
ifelsestmt ::= testexpr . c_stmts_opt JUMP_FORWARD else_suite _come_froms
ifelsestmt ::= testexpr . c_stmts_opt JUMP_FORWARD else_suite opt_come_from_except
ifelsestmt ::= testexpr . c_stmts_opt jf_cfs else_suite \e_opt_come_from_except
ifelsestmt ::= testexpr . c_stmts_opt jf_cfs else_suite opt_come_from_except
ifelsestmt ::= testexpr . c_stmts_opt jump_forward_else else_suite \e__come_froms
ifelsestmt ::= testexpr . c_stmts_opt jump_forward_else else_suite _come_froms
ifelsestmt ::= testexpr . stmts jf_cfs \e_else_suite_opt \e_opt_come_from_except
ifelsestmt ::= testexpr . stmts jf_cfs \e_else_suite_opt opt_come_from_except
ifelsestmt ::= testexpr . stmts jf_cfs else_suite_opt \e_opt_come_from_except
ifelsestmt ::= testexpr . stmts jf_cfs else_suite_opt opt_come_from_except
ifelsestmt ::= testexpr \e_c_stmts_opt . JUMP_FORWARD else_suite \e__come_froms
ifelsestmt ::= testexpr \e_c_stmts_opt . JUMP_FORWARD else_suite \e_opt_come_from_except
ifelsestmt ::= testexpr \e_c_stmts_opt . JUMP_FORWARD else_suite _come_froms
ifelsestmt ::= testexpr \e_c_stmts_opt . JUMP_FORWARD else_suite opt_come_from_except
ifelsestmt ::= testexpr \e_c_stmts_opt . jf_cfs else_suite \e_opt_come_from_except
ifelsestmt ::= testexpr \e_c_stmts_opt . jf_cfs else_suite opt_come_from_except
ifelsestmt ::= testexpr \e_c_stmts_opt . jump_forward_else else_suite \e__come_froms
ifelsestmt ::= testexpr \e_c_stmts_opt . jump_forward_else else_suite _come_froms
ifelsestmt ::= testexpr c_stmts . come_froms else_suite come_froms
ifelsestmt ::= testexpr c_stmts_opt . JUMP_FORWARD else_suite \e__come_froms
ifelsestmt ::= testexpr c_stmts_opt . JUMP_FORWARD else_suite \e_opt_come_from_except
ifelsestmt ::= testexpr c_stmts_opt . JUMP_FORWARD else_suite _come_froms
ifelsestmt ::= testexpr c_stmts_opt . JUMP_FORWARD else_suite opt_come_from_except
ifelsestmt ::= testexpr c_stmts_opt . jf_cfs else_suite \e_opt_come_from_except
ifelsestmt ::= testexpr c_stmts_opt . jf_cfs else_suite opt_come_from_except
ifelsestmt ::= testexpr c_stmts_opt . jump_forward_else else_suite \e__come_froms
ifelsestmt ::= testexpr c_stmts_opt . jump_forward_else else_suite _come_froms
ifelsestmt ::= testexpr stmts . jf_cfs \e_else_suite_opt \e_opt_come_from_except
ifelsestmt ::= testexpr stmts . jf_cfs \e_else_suite_opt opt_come_from_except
ifelsestmt ::= testexpr stmts . jf_cfs else_suite_opt \e_opt_come_from_except
ifelsestmt ::= testexpr stmts . jf_cfs else_suite_opt opt_come_from_except
ifelsestmtl ::= testexpr . c_stmts cf_pt else_suite
ifelsestmtl ::= testexpr . c_stmts_opt cf_jf_else else_suitel
ifelsestmtl ::= testexpr . c_stmts_opt cf_jump_back else_suitel
ifelsestmtl ::= testexpr . c_stmts_opt jb_cfs else_suitel
ifelsestmtl ::= testexpr . c_stmts_opt jb_cfs else_suitel JUMP_BACK come_froms
ifelsestmtl ::= testexpr . c_stmts_opt jb_else else_suitel
ifelsestmtl ::= testexpr . c_stmts_opt jump_forward_else else_suitec
ifelsestmtl ::= testexpr \e_c_stmts_opt . cf_jf_else else_suitel
ifelsestmtl ::= testexpr \e_c_stmts_opt . cf_jump_back else_suitel
ifelsestmtl ::= testexpr \e_c_stmts_opt . jb_cfs else_suitel
ifelsestmtl ::= testexpr \e_c_stmts_opt . jb_cfs else_suitel JUMP_BACK come_froms
ifelsestmtl ::= testexpr \e_c_stmts_opt . jb_else else_suitel
ifelsestmtl ::= testexpr \e_c_stmts_opt . jump_forward_else else_suitec
ifelsestmtl ::= testexpr c_stmts . cf_pt else_suite
ifelsestmtl ::= testexpr c_stmts_opt . cf_jf_else else_suitel
ifelsestmtl ::= testexpr c_stmts_opt . cf_jump_back else_suitel
ifelsestmtl ::= testexpr c_stmts_opt . jb_cfs else_suitel
ifelsestmtl ::= testexpr c_stmts_opt . jb_cfs else_suitel JUMP_BACK come_froms
ifelsestmtl ::= testexpr c_stmts_opt . jb_else else_suitel
ifelsestmtl ::= testexpr c_stmts_opt . jump_forward_else else_suitec
iflaststmtl ::= testexpr . c_stmts
iflaststmtl ::= testexpr . c_stmts JUMP_BACK
iflaststmtl ::= testexpr . c_stmts JUMP_BACK COME_FROM_LOOP
iflaststmtl ::= testexpr . c_stmts JUMP_BACK POP_BLOCK
iflaststmtl ::= testexpr c_stmts . 
iflaststmtl ::= testexpr c_stmts . JUMP_BACK
iflaststmtl ::= testexpr c_stmts . JUMP_BACK COME_FROM_LOOP
iflaststmtl ::= testexpr c_stmts . JUMP_BACK POP_BLOCK
ifpoplaststmtl ::= testexpr . POP_TOP \e_c_stmts_opt
ifpoplaststmtl ::= testexpr . POP_TOP c_stmts_opt
ifstmt ::= testexpr . _ifstmts_jump
ifstmtl ::= testexpr . _ifstmts_jumpl
import ::= LOAD_CONST . LOAD_CONST alias
import_as37 ::= LOAD_CONST . LOAD_CONST importlist37 store POP_TOP
import_from ::= LOAD_CONST . LOAD_CONST IMPORT_NAME importlist POP_TOP
import_from ::= LOAD_CONST . LOAD_CONST importlist POP_TOP
import_from37 ::= LOAD_CONST . LOAD_CONST IMPORT_NAME_ATTR importlist37 POP_TOP
import_from_as37 ::= LOAD_CONST . LOAD_CONST import_from_attr37 store POP_TOP
import_from_star ::= LOAD_CONST . LOAD_CONST IMPORT_NAME IMPORT_STAR
import_from_star ::= LOAD_CONST . LOAD_CONST IMPORT_NAME_ATTR IMPORT_STAR
importmultiple ::= LOAD_CONST . LOAD_CONST alias imports_cont
jb_cfs ::= \e_come_from_opt . JUMP_BACK come_froms
jmp_false ::= POP_JUMP_IF_FALSE . 
joined_str ::= expr . expr expr BUILD_STRING_3
joined_str ::= expr . expr expr expr expr BUILD_STRING_5
joined_str ::= expr . expr expr expr expr expr expr BUILD_STRING_7
joined_str ::= expr expr . expr BUILD_STRING_3
joined_str ::= expr expr . expr expr expr BUILD_STRING_5
joined_str ::= expr expr . expr expr expr expr expr BUILD_STRING_7
joined_str ::= expr expr expr . BUILD_STRING_3
joined_str ::= expr expr expr . expr expr BUILD_STRING_5
joined_str ::= expr expr expr . expr expr expr expr BUILD_STRING_7
joined_str ::= expr expr expr BUILD_STRING_3 . 
joined_str ::= expr expr expr expr . expr BUILD_STRING_5
joined_str ::= expr expr expr expr . expr expr expr BUILD_STRING_7
l_stmts ::= _stmts . 
l_stmts ::= _stmts . lastl_stmt
l_stmts ::= l_stmts . lstmt
l_stmts ::= l_stmts lstmt . 
l_stmts ::= lstmt . 
l_stmts_opt ::= l_stmts . 
lc_setup_finally ::= LOAD_CONST . SETUP_FINALLY
lstmt ::= stmt . 
mkfuncdeco ::= expr . mkfuncdeco CALL_FUNCTION_1
mkfuncdeco ::= expr . mkfuncdeco0 CALL_FUNCTION_1
named_expr ::= expr . DUP_TOP store
pop_ex_return ::= return_expr . ROT_FOUR POP_EXCEPT RETURN_VALUE
pop_return ::= POP_TOP . return_expr RETURN_VALUE
popb_return ::= return_expr . POP_BLOCK RETURN_VALUE
pos_arg ::= expr . 
ret_and ::= expr . JUMP_IF_FALSE_OR_POP return_expr_or_cond COME_FROM
ret_or ::= expr . JUMP_IF_TRUE_OR_POP return_expr_or_cond COME_FROM
return ::= return_expr . RETURN_END_IF
return ::= return_expr . RETURN_VALUE
return ::= return_expr . RETURN_VALUE COME_FROM
return ::= return_expr . discard_tops RETURN_VALUE
return_expr ::= expr . 
return_expr_lambda ::= return_expr . RETURN_VALUE_LAMBDA
return_expr_lambda ::= return_expr . RETURN_VALUE_LAMBDA LAMBDA_MARKER
return_if_stmt ::= return_expr . RETURN_END_IF
return_if_stmt ::= return_expr . RETURN_END_IF POP_BLOCK
return_if_stmts ::= _stmts . return_if_stmt \e__come_froms
return_if_stmts ::= _stmts . return_if_stmt _come_froms
returns ::= _stmts . return
returns ::= _stmts . return_if_stmt
sstmt ::= sstmt . RETURN_LAST
sstmt ::= stmt . 
stmt ::= assign . 
stmt ::= call_stmt . 
stmt ::= expr_stmt . 
stmt ::= for38 . 
stmts ::= sstmt . 
stmts ::= stmts . sstmt
stmts ::= stmts sstmt . 
store ::= STORE_FAST . 
store ::= expr . STORE_ATTR
store_subscript ::= expr . expr STORE_SUBSCR
store_subscript ::= expr expr . STORE_SUBSCR
subscript ::= expr . expr BINARY_SUBSCR
subscript ::= expr expr . BINARY_SUBSCR
subscript2 ::= expr . expr DUP_TOP_TWO BINARY_SUBSCR
subscript2 ::= expr expr . DUP_TOP_TWO BINARY_SUBSCR
testexpr ::= testfalse . 
testexpr_cf ::= testexpr . come_froms
testfalse ::= expr . jmp_false
testfalse ::= expr jmp_false . 
testfalse_not_and ::= expr . jmp_false expr jmp_true COME_FROM
testfalse_not_and ::= expr jmp_false . expr jmp_true COME_FROM
testfalse_not_and ::= expr jmp_false expr . jmp_true COME_FROM
testfalse_not_or ::= expr . jmp_false expr jmp_false COME_FROM
testfalse_not_or ::= expr jmp_false . expr jmp_false COME_FROM
testfalse_not_or ::= expr jmp_false expr . jmp_false COME_FROM
testfalsel ::= expr . jmp_true
testtrue ::= expr . jmp_true
tryfinally38astmt ::= LOAD_CONST . SETUP_FINALLY \e_suite_stmts_opt POP_BLOCK BEGIN_FINALLY COME_FROM_FINALLY POP_FINALLY POP_TOP \e_suite_stmts_opt END_FINALLY POP_TOP
tryfinally38astmt ::= LOAD_CONST . SETUP_FINALLY \e_suite_stmts_opt POP_BLOCK BEGIN_FINALLY COME_FROM_FINALLY POP_FINALLY POP_TOP suite_stmts_opt END_FINALLY POP_TOP
tryfinally38astmt ::= LOAD_CONST . SETUP_FINALLY suite_stmts_opt POP_BLOCK BEGIN_FINALLY COME_FROM_FINALLY POP_FINALLY POP_TOP \e_suite_stmts_opt END_FINALLY POP_TOP
tryfinally38astmt ::= LOAD_CONST . SETUP_FINALLY suite_stmts_opt POP_BLOCK BEGIN_FINALLY COME_FROM_FINALLY POP_FINALLY POP_TOP suite_stmts_opt END_FINALLY POP_TOP
unary_not ::= expr . UNARY_NOT
unary_op ::= expr . unary_operator
while1stmt ::= \e__come_froms . l_stmts COME_FROM JUMP_BACK COME_FROM_LOOP
while1stmt ::= \e__come_froms l_stmts . COME_FROM JUMP_BACK COME_FROM_LOOP
whileTruestmt ::= \e__come_froms . l_stmts JUMP_BACK POP_BLOCK
whileTruestmt ::= \e__come_froms l_stmts . JUMP_BACK POP_BLOCK
whileTruestmt38 ::= \e__come_froms . l_stmts JUMP_BACK
whileTruestmt38 ::= \e__come_froms . l_stmts JUMP_BACK COME_FROM_EXCEPT_CLAUSE
whileTruestmt38 ::= \e__come_froms . pass JUMP_BACK
whileTruestmt38 ::= \e__come_froms \e_pass . JUMP_BACK
whileTruestmt38 ::= \e__come_froms l_stmts . JUMP_BACK
whileTruestmt38 ::= \e__come_froms l_stmts . JUMP_BACK COME_FROM_EXCEPT_CLAUSE
whilestmt38 ::= \e__come_froms . testexpr \e_l_stmts_opt COME_FROM JUMP_BACK POP_BLOCK
whilestmt38 ::= \e__come_froms . testexpr \e_l_stmts_opt JUMP_BACK POP_BLOCK
whilestmt38 ::= \e__come_froms . testexpr \e_l_stmts_opt JUMP_BACK come_froms
whilestmt38 ::= \e__come_froms . testexpr l_stmts JUMP_BACK
whilestmt38 ::= \e__come_froms . testexpr l_stmts come_froms
whilestmt38 ::= \e__come_froms . testexpr l_stmts_opt COME_FROM JUMP_BACK POP_BLOCK
whilestmt38 ::= \e__come_froms . testexpr l_stmts_opt JUMP_BACK POP_BLOCK
whilestmt38 ::= \e__come_froms . testexpr l_stmts_opt JUMP_BACK come_froms
whilestmt38 ::= \e__come_froms . testexpr returns POP_BLOCK
whilestmt38 ::= \e__come_froms testexpr . l_stmts JUMP_BACK
whilestmt38 ::= \e__come_froms testexpr . l_stmts come_froms
whilestmt38 ::= \e__come_froms testexpr . l_stmts_opt COME_FROM JUMP_BACK POP_BLOCK
whilestmt38 ::= \e__come_froms testexpr . l_stmts_opt JUMP_BACK POP_BLOCK
whilestmt38 ::= \e__come_froms testexpr . l_stmts_opt JUMP_BACK come_froms
whilestmt38 ::= \e__come_froms testexpr . returns POP_BLOCK
whilestmt38 ::= \e__come_froms testexpr \e_l_stmts_opt . COME_FROM JUMP_BACK POP_BLOCK
whilestmt38 ::= \e__come_froms testexpr \e_l_stmts_opt . JUMP_BACK POP_BLOCK
whilestmt38 ::= \e__come_froms testexpr \e_l_stmts_opt . JUMP_BACK come_froms
whilestmt38 ::= \e__come_froms testexpr l_stmts . JUMP_BACK
whilestmt38 ::= \e__come_froms testexpr l_stmts . come_froms
whilestmt38 ::= \e__come_froms testexpr l_stmts_opt . COME_FROM JUMP_BACK POP_BLOCK
whilestmt38 ::= \e__come_froms testexpr l_stmts_opt . JUMP_BACK POP_BLOCK
whilestmt38 ::= \e__come_froms testexpr l_stmts_opt . JUMP_BACK come_froms
yield ::= expr . YIELD_VALUE
yield_from ::= expr . GET_YIELD_FROM_ITER LOAD_CONST YIELD_FROM
Instruction context:
   
 L. 242        66  POP_TOP          
->             68_70  JUMP_ABSOLUTE       340  'to 340'
                72_0  COME_FROM            44  '44'


def retry_request--- This code section failed: ---

 L. 237         0  LOAD_GLOBAL              time
                2  LOAD_METHOD              time
                4  CALL_METHOD_0         0  ''
                6  STORE_FAST               't0'

 L. 238         8  LOAD_CONST               None
               10  STORE_FAST               'response'

 L. 239        12  LOAD_GLOBAL              range
               14  LOAD_DEREF               'retry'
               16  LOAD_CONST               1
               18  BINARY_ADD       
               20  CALL_FUNCTION_1       1  ''
               22  GET_ITER         
            24_26  FOR_ITER            340  'to 340'
               28  STORE_FAST               'i'

 L. 240        30  LOAD_GLOBAL              time
               32  LOAD_METHOD              time
               34  CALL_METHOD_0         0  ''
               36  LOAD_FAST                't0'
               38  BINARY_SUBTRACT  
               40  LOAD_DEREF               'timeout'
               42  COMPARE_OP               >
               44  POP_JUMP_IF_FALSE    72  'to 72'

 L. 241        46  LOAD_GLOBAL              LOGGER
               48  LOAD_METHOD              warning
               50  LOAD_GLOBAL              PREFIX
               52  FORMAT_VALUE          0  ''
               54  LOAD_STR                 'Timeout for request reached. '
               56  LOAD_GLOBAL              HELP_MSG
               58  FORMAT_VALUE          0  ''
               60  BUILD_STRING_3        3 
               62  CALL_METHOD_1         1  ''
               64  POP_TOP          

 L. 242        66  POP_TOP          
            68_70  JUMP_ABSOLUTE       340  'to 340'
             72_0  COME_FROM            44  '44'

 L. 244        72  LOAD_DEREF               'request_func'
               74  LOAD_DEREF               'args'
               76  LOAD_DEREF               'kwargs'
               78  CALL_FUNCTION_EX_KW     1  'keyword and positional arguments'
               80  STORE_FAST               'response'

 L. 245        82  LOAD_FAST                'response'
               84  LOAD_CONST               None
               86  COMPARE_OP               is
               88  POP_JUMP_IF_FALSE   126  'to 126'

 L. 246        90  LOAD_GLOBAL              LOGGER
               92  LOAD_METHOD              warning
               94  LOAD_GLOBAL              PREFIX
               96  FORMAT_VALUE          0  ''
               98  LOAD_STR                 'Received no response from the request. '
              100  LOAD_GLOBAL              HELP_MSG
              102  FORMAT_VALUE          0  ''
              104  BUILD_STRING_3        3 
              106  CALL_METHOD_1         1  ''
              108  POP_TOP          

 L. 247       110  LOAD_GLOBAL              time
              112  LOAD_METHOD              sleep
              114  LOAD_CONST               2
              116  LOAD_FAST                'i'
              118  BINARY_POWER     
              120  CALL_METHOD_1         1  ''
              122  POP_TOP          

 L. 248       124  JUMP_BACK            24  'to 24'
            126_0  COME_FROM            88  '88'

 L. 250       126  LOAD_DEREF               'progress_total'
              128  POP_JUMP_IF_FALSE   144  'to 144'

 L. 251       130  LOAD_DEREF               'self'
              132  LOAD_METHOD              _show_upload_progress
              134  LOAD_DEREF               'progress_total'
              136  LOAD_FAST                'response'
              138  CALL_METHOD_2         2  ''
              140  POP_TOP          
              142  JUMP_FORWARD        158  'to 158'
            144_0  COME_FROM           128  '128'

 L. 252       144  LOAD_DEREF               'stream_response'
              146  POP_JUMP_IF_FALSE   158  'to 158'

 L. 253       148  LOAD_DEREF               'self'
              150  LOAD_METHOD              _iterate_content
              152  LOAD_FAST                'response'
              154  CALL_METHOD_1         1  ''
              156  POP_TOP          
            158_0  COME_FROM           146  '146'
            158_1  COME_FROM           142  '142'

 L. 255       158  LOAD_GLOBAL              HTTPStatus
              160  LOAD_ATTR                OK
              162  LOAD_FAST                'response'
              164  LOAD_ATTR                status_code
              166  DUP_TOP          
              168  ROT_THREE        
              170  COMPARE_OP               <=
              172  POP_JUMP_IF_FALSE   184  'to 184'
              174  LOAD_GLOBAL              HTTPStatus
              176  LOAD_ATTR                MULTIPLE_CHOICES
              178  COMPARE_OP               <
              180  POP_JUMP_IF_FALSE   212  'to 212'
              182  JUMP_FORWARD        188  'to 188'
            184_0  COME_FROM           172  '172'
              184  POP_TOP          
              186  JUMP_FORWARD        212  'to 212'
            188_0  COME_FROM           182  '182'

 L. 257       188  LOAD_DEREF               'kwargs'
              190  LOAD_METHOD              get
              192  LOAD_STR                 'metrics'
              194  CALL_METHOD_1         1  ''
              196  POP_JUMP_IF_FALSE   204  'to 204'

 L. 258       198  BUILD_MAP_0           0 
              200  LOAD_DEREF               'self'
              202  STORE_ATTR               metrics_upload_failed_queue
            204_0  COME_FROM           196  '196'

 L. 259       204  LOAD_FAST                'response'
              206  ROT_TWO          
              208  POP_TOP          
              210  RETURN_VALUE     
            212_0  COME_FROM           186  '186'
            212_1  COME_FROM           180  '180'

 L. 261       212  LOAD_FAST                'i'
              214  LOAD_CONST               0
              216  COMPARE_OP               ==
          218_220  POP_JUMP_IF_FALSE   276  'to 276'

 L. 263       222  LOAD_DEREF               'self'
              224  LOAD_METHOD              _get_failure_message
              226  LOAD_FAST                'response'
              228  LOAD_DEREF               'retry'
              230  LOAD_DEREF               'timeout'
              232  CALL_METHOD_3         3  ''
              234  STORE_FAST               'message'

 L. 265       236  LOAD_DEREF               'verbose'
          238_240  POP_JUMP_IF_FALSE   276  'to 276'

 L. 266       242  LOAD_GLOBAL              LOGGER
              244  LOAD_METHOD              warning
              246  LOAD_GLOBAL              PREFIX
              248  FORMAT_VALUE          0  ''
              250  LOAD_FAST                'message'
              252  FORMAT_VALUE          0  ''
              254  LOAD_STR                 ' '
              256  LOAD_GLOBAL              HELP_MSG
              258  FORMAT_VALUE          0  ''
              260  LOAD_STR                 ' ('
              262  LOAD_FAST                'response'
              264  LOAD_ATTR                status_code
              266  FORMAT_VALUE          0  ''
              268  LOAD_STR                 ')'
              270  BUILD_STRING_7        7 
              272  CALL_METHOD_1         1  ''
              274  POP_TOP          
            276_0  COME_FROM           238  '238'
            276_1  COME_FROM           218  '218'

 L. 268       276  LOAD_DEREF               'self'
              278  LOAD_METHOD              _should_retry
              280  LOAD_FAST                'response'
              282  LOAD_ATTR                status_code
              284  CALL_METHOD_1         1  ''
          286_288  POP_JUMP_IF_TRUE    324  'to 324'

 L. 269       290  LOAD_GLOBAL              LOGGER
              292  LOAD_METHOD              warning
              294  LOAD_GLOBAL              PREFIX
              296  FORMAT_VALUE          0  ''
              298  LOAD_STR                 'Request failed. '
              300  LOAD_GLOBAL              HELP_MSG
              302  FORMAT_VALUE          0  ''
              304  LOAD_STR                 ' ('
              306  LOAD_FAST                'response'
              308  LOAD_ATTR                status_code
              310  FORMAT_VALUE          0  ''
              312  BUILD_STRING_5        5 
              314  CALL_METHOD_1         1  ''
              316  POP_TOP          

 L. 270       318  POP_TOP          
          320_322  JUMP_ABSOLUTE       340  'to 340'
            324_0  COME_FROM           286  '286'

 L. 272       324  LOAD_GLOBAL              time
              326  LOAD_METHOD              sleep
              328  LOAD_CONST               2
              330  LOAD_FAST                'i'
              332  BINARY_POWER     
              334  CALL_METHOD_1         1  ''
              336  POP_TOP          
              338  JUMP_BACK            24  'to 24'

 L. 275       340  LOAD_FAST                'response'
              342  LOAD_CONST               None
              344  COMPARE_OP               is
          346_348  POP_JUMP_IF_FALSE   382  'to 382'
              350  LOAD_DEREF               'kwargs'
              352  LOAD_METHOD              get
              354  LOAD_STR                 'metrics'
              356  CALL_METHOD_1         1  ''
          358_360  POP_JUMP_IF_FALSE   382  'to 382'

 L. 276       362  LOAD_DEREF               'self'
              364  LOAD_ATTR                metrics_upload_failed_queue
              366  LOAD_METHOD              update
              368  LOAD_DEREF               'kwargs'
              370  LOAD_METHOD              get
              372  LOAD_STR                 'metrics'
              374  LOAD_CONST               None
              376  CALL_METHOD_2         2  ''
              378  CALL_METHOD_1         1  ''
              380  POP_TOP          
            382_0  COME_FROM           358  '358'
            382_1  COME_FROM           346  '346'

 L. 278       382  LOAD_FAST                'response'
              384  RETURN_VALUE     
               -1  RETURN_LAST      

Parse error at or near `JUMP_ABSOLUTE' instruction at offset 68_70


if thread:
    threading.Thread(target=retry_request, daemon=True).start()
else:
    return retry_request(